unicoder.py
text_unicoder-1.3.3501.data/data/data/LICENSE
text_unicoder-1.3.3501.data/data/data/README.md
text_unicoder-1.3.3501.data/data/data/unicoder.py.tests.py
text_unicoder-1.3.3501.dist-info/LICENSE
text_unicoder-1.3.3501.dist-info/METADATA
text_unicoder-1.3.3501.dist-info/WHEEL
text_unicoder-1.3.3501.dist-info/entry_points.txt
text_unicoder-1.3.3501.dist-info/top_level.txt
text_unicoder-1.3.3501.dist-info/RECORD
