Metadata-Version: 2.1
Name: text_unicoder
Version: 1.3.3501
Summary: unicode text generator to make flip turned bold italic greek fraktur cursive script from ascii input
Author-email: "Guido U. Draheim" <Guido.Draheim@gmx.de>
License:                                  Apache License
Project-URL: homepage, https://github.com/gdraheim/text_unicoder
Project-URL: repository, https://github.com/gdraheim/text_unicoder.git
Project-URL: issues, https://github.com/gdraheim/text_unicoder/issues
Classifier: License :: OSI Approved :: Apache Software License
Classifier: Operating System :: OS Independent
Classifier: Environment :: Console
Classifier: Topic :: Text Processing :: Filters
Classifier: Typing :: Typed
License-File: LICENSE
Provides-Extra: dev
Requires-Dist: build; extra == "dev"
